pymdsm/__init__.py
pymdsm/pymdsm.py
pymdsm-0.0.3.dist-info/LICENSE
pymdsm-0.0.3.dist-info/METADATA
pymdsm-0.0.3.dist-info/WHEEL
pymdsm-0.0.3.dist-info/top_level.txt
pymdsm-0.0.3.dist-info/RECORD
